pico_acme/__init__.py
pico_acme/core.py
pico_acme/route53.py
pico_acme/version
pico_acme/version.py
pico_acme-0.0.5.dist-info/METADATA
pico_acme-0.0.5.dist-info/WHEEL
pico_acme-0.0.5.dist-info/license.md
pico_acme-0.0.5.dist-info/top_level.txt
pico_acme-0.0.5.dist-info/RECORD
