Metadata-Version: 2.1
Name: pico_acme
Version: 0.0.5
Summary: Pico ACME: tiny ACMEv2 client
Home-page: https://github.com/aapeliv/pico-acme
Author: Aapeli Vuorinen
Project-URL: GitHub, https://github.com/aapeliv/pico-acme
Project-URL: Bug Tracker, https://github.com/aapeliv/pico-acme/issues
Classifier: Programming Language :: Python :: 3
Classifier: License :: OSI Approved :: Apache Software License
Classifier: Operating System :: OS Independent
Requires-Python: >=3.8
License-File: license.md
Requires-Dist: acme ==2.9.0
Requires-Dist: cryptography >=3.2.1
Requires-Dist: PyOpenSSL !=23.1.0,>=17.5.0
Requires-Dist: pyrfc3339
